lkr/__init__.py
lkr/auth_service.py
lkr/classes.py
lkr/constants.py
lkr/custom_types.py
lkr/exceptions.py
lkr/logger.py
lkr/main.py
lkr/auth/__init__.py
lkr/auth/main.py
lkr/auth/oauth.py
lkr/mcp/classes.py
lkr/mcp/main.py
lkr/mcp/utils.py
lkr/observability/classes.py
lkr/observability/embed_container.html
lkr/observability/main.py
lkr/observability/utils.py
lkr/tools/classes.py
lkr/tools/main.py
lkr_dev_cli-0.0.32.dist-info/METADATA
lkr_dev_cli-0.0.32.dist-info/WHEEL
lkr_dev_cli-0.0.32.dist-info/entry_points.txt
lkr_dev_cli-0.0.32.dist-info/licenses/LICENSE
lkr_dev_cli-0.0.32.dist-info/RECORD
