Metadata-Version: 2.4
Name: lkr-dev-cli
Version: 0.0.32
Summary: lkr: a command line interface for looker
Author: bwebs
License-Expression: MIT
License-File: LICENSE
Requires-Python: >=3.12
Requires-Dist: looker-sdk>=25.4.0
Requires-Dist: pydantic>=2.11.4
Requires-Dist: pydash>=8.0.5
Provides-Extra: all
Requires-Dist: cryptography>=42.0.0; extra == 'all'
Requires-Dist: duckdb>=1.2.2; extra == 'all'
Requires-Dist: fastapi[standard]>=0.115.12; extra == 'all'
Requires-Dist: mcp[cli]>=1.9.2; extra == 'all'
Requires-Dist: questionary>=2.1.0; extra == 'all'
Requires-Dist: requests>=2.31.0; extra == 'all'
Requires-Dist: selenium>=4.32.0; extra == 'all'
Requires-Dist: structlog>=25.3.0; extra == 'all'
Requires-Dist: typer>=0.15.2; extra == 'all'
Provides-Extra: cli
Requires-Dist: cryptography>=42.0.0; extra == 'cli'
Requires-Dist: questionary>=2.1.0; extra == 'cli'
Requires-Dist: requests>=2.31.0; extra == 'cli'
Requires-Dist: structlog>=25.3.0; extra == 'cli'
Requires-Dist: typer>=0.15.2; extra == 'cli'
Provides-Extra: mcp
Requires-Dist: duckdb>=1.2.2; extra == 'mcp'
Requires-Dist: fastapi[standard]>=0.115.12; extra == 'mcp'
Requires-Dist: mcp[cli]>=1.9.2; extra == 'mcp'
Provides-Extra: observability
Requires-Dist: fastapi[standard]>=0.115.12; extra == 'observability'
Requires-Dist: selenium>=4.32.0; extra == 'observability'
Provides-Extra: tools
Requires-Dist: fastapi[standard]>=0.115.12; extra == 'tools'
